amocrm/__init__.py
amocrm/conf.py
amocrm/dictwrap.py
amocrm/exceptions.py
amocrm/fields.py
amocrm/manager.py
amocrm/util.py
amocrm/values.py
amocrm/entities/__init__.py
amocrm/entities/contact.py
amocrm/entities/customer.py
amocrm/entities/entity.py
amocrm/entities/lead.py
amocrm-0.7.7.dist-info/DESCRIPTION.rst
amocrm-0.7.7.dist-info/METADATA
amocrm-0.7.7.dist-info/RECORD
amocrm-0.7.7.dist-info/WHEEL
amocrm-0.7.7.dist-info/metadata.json
amocrm-0.7.7.dist-info/top_level.txt
